<SinModMenu>
    <set xpath="/windows/window[@name='mainMenuLogo']/texture[@name='gameLogo']/@anchor_top">#cam,0.5,450</set>
	<set xpath="/windows/window[@name='mainMenuLogo']/texture[@name='gameLogo']/@anchor_left">#cam,0.5,-1000</set>
	<set xpath="/windows/window[@name='mainMenuLogo']/texture[@name='gameLogo']/@anchor_bottom">#cam,0.5,150</set>

	<set xpath="/windows/window[@name='mainMenuLogo']/@depth">3</set>
    <set xpath="/windows/window[@name='mainMenu']/@pos">-550,0</set>


    <set xpath="/windows/window[@name='menuBackground']/texture[@name='bgTexture']/@texture">@modfolder:Textures/UI/background_Xmas.png</set>
    <set xpath="/windows/window[@name='mainMenuLogo']/texture[@name='gameLogo']/@texture">@modfolder:Textures/UI/logo_Xmas.png</set>

</SinModMenu>